Workbook

Sheet Start Here
A1: Seller Margin Toolkit
A3: Yellow cells are inputs. Everything else calculates itself.
A4: 1. Settings: enter your marketplace fee rates (check each marketplace's official fee page; defaults are US estimates).
A5: 2. Inventory: list your products and unit costs.
A6: 3. Sales Log: add one row per sale. Fees and profit fill in automatically.
A7: 4. Ad Spend: log ad spend to see return on ad spend (ROAS).
A8: 5. Dashboard: total revenue, fees, profit, margin after ads and a tax set-aside estimate.
A9: Not financial or tax advice. Tax rate is your own assumption; ask an accountant.

Sheet Dashboard
A1: Dashboard
A3: Total revenue | B3: =SUMPRODUCT('Sales Log'!E2:E1001,'Sales Log'!D2:D1001)+SUM('Sales Log'!F2:F1001)
A4: Total fees | B4: =SUM('Sales Log'!I2:I1001)
A5: Total net profit | B5: =SUM('Sales Log'!J2:J1001)
A6: Total ad spend | B6: =SUM('Ad Spend'!C2:C61)
A7: Profit after ads | B7: =B5-B6
A8: Margin after ads | B8: =IF(B3=0,0,B7/B3)
A9: Tax set-aside (see Settings) | B9: =MAX(0,B7)*Settings!B8/100
A10: Per-quarter set-aside (total ÷ 4, use with a full year of data) | B10: =B9/4
A12: Items to reorder | B12: =COUNTIF(Inventory!G2:G201,"REORDER")

Sheet Settings
A1: Marketplace | B1: Listing fee ($) | C1: Fee % of item+shipping | D1: Payment % | E1: Payment fixed ($) | F1: Per-order fee ($)
A2: Etsy | B2: 0.2 | C2: 6.5 | D2: 3 | E2: 0.25 | F2: 0
A3: eBay | B3: 0 | C3: 13.6 | D3: 0 | E3: 0 | F3: 0.4
A4: Amazon | B4: 0 | C4: 15 | D4: 0 | E4: 0 | F4: 0
A5: Other | B5: 0 | C5: 0 | D5: 0 | E5: 0 | F5: 0
A8: Tax set-aside % of profit | B8: 25
A9: Fee defaults are estimates (2026-10-19). Verify before relying on them.

Sheet Inventory
A1: SKU / Product | B1: Unit cost ($) | C1: Qty bought | D1: Qty sold | E1: In stock | F1: Reorder at | G1: Status
D2: =SUMIF('Sales Log'!$B:$B,A2,'Sales Log'!$D:$D) | E2: =IF(A2="","",C2-D2) | G2: =IF(A2="","",IF(E2<=F2,"REORDER","OK"))
D3: =SUMIF('Sales Log'!$B:$B,A3,'Sales Log'!$D:$D) | E3: =IF(A3="","",C3-D3) | G3: =IF(A3="","",IF(E3<=F3,"REORDER","OK"))
D4: =SUMIF('Sales Log'!$B:$B,A4,'Sales Log'!$D:$D) | E4: =IF(A4="","",C4-D4) | G4: =IF(A4="","",IF(E4<=F4,"REORDER","OK"))
D5: =SUMIF('Sales Log'!$B:$B,A5,'Sales Log'!$D:$D) | E5: =IF(A5="","",C5-D5) | G5: =IF(A5="","",IF(E5<=F5,"REORDER","OK"))
D6: =SUMIF('Sales Log'!$B:$B,A6,'Sales Log'!$D:$D) | E6: =IF(A6="","",C6-D6) | G6: =IF(A6="","",IF(E6<=F6,"REORDER","OK"))
D7: =SUMIF('Sales Log'!$B:$B,A7,'Sales Log'!$D:$D) | E7: =IF(A7="","",C7-D7) | G7: =IF(A7="","",IF(E7<=F7,"REORDER","OK"))
D8: =SUMIF('Sales Log'!$B:$B,A8,'Sales Log'!$D:$D) | E8: =IF(A8="","",C8-D8) | G8: =IF(A8="","",IF(E8<=F8,"REORDER","OK"))
D9: =SUMIF('Sales Log'!$B:$B,A9,'Sales Log'!$D:$D) | E9: =IF(A9="","",C9-D9) | G9: =IF(A9="","",IF(E9<=F9,"REORDER","OK"))
D10: =SUMIF('Sales Log'!$B:$B,A10,'Sales Log'!$D:$D) | E10: =IF(A10="","",C10-D10) | G10: =IF(A10="","",IF(E10<=F10,"REORDER","OK"))
D11: =SUMIF('Sales Log'!$B:$B,A11,'Sales Log'!$D:$D) | E11: =IF(A11="","",C11-D11) | G11: =IF(A11="","",IF(E11<=F11,"REORDER","OK"))
D12: =SUMIF('Sales Log'!$B:$B,A12,'Sales Log'!$D:$D) | E12: =IF(A12="","",C12-D12) | G12: =IF(A12="","",IF(E12<=F12,"REORDER","OK"))
D13: =SUMIF('Sales Log'!$B:$B,A13,'Sales Log'!$D:$D) | E13: =IF(A13="","",C13-D13) | G13: =IF(A13="","",IF(E13<=F13,"REORDER","OK"))
... D201: =SUMIF('Sales Log'!$B:$B,A201,'Sales Log'!$D:$D) | E201: =IF(A201="","",C201-D201) | G201: =IF(A201="","",IF(E201<=F201,"REORDER","OK"))

Sheet Sales Log
A1: Date | B1: Product (match Inventory) | C1: Marketplace | D1: Qty | E1: Item price ($) | F1: Shipping charged ($) | G1: Your shipping cost ($) | H1: Item cost ($) | I1: Fees ($) | J1: Net profit ($) | K1: Margin
H2: =IFERROR(VLOOKUP(B2,Inventory!$A:$B,2,FALSE)*D2,0) | I2: =IF(C2="",0,IFERROR(VLOOKUP(C2,Settings!$A$2:$F$5,2,FALSE)+(E2*D2+F2)*VLOOKUP(C2,Settings!$A$2:$F$5,3,FALSE)/100+(E2*D2+F2)*VLOOKUP(C2,Settings!$A$2:$F$5,4,FALSE)/100+VLOOKUP(C2,Settings!$A$2:$F$5,5,FALSE)+VLOOKUP(C2,Settings!$A$2:$F$5,6,FALSE),0)) | J2: =IF(B2="","",IF(ISNA(MATCH(B2,Inventory!$A$2:$A$201,0)),"Check product",E2*D2+F2-I2-G2-H2)) | K2: =IF(OR(B2="",NOT(ISNUMBER(J2)),E2*D2+F2=0),"",J2/(E2*D2+F2))
H3: =IFERROR(VLOOKUP(B3,Inventory!$A:$B,2,FALSE)*D3,0) | I3: =IF(C3="",0,IFERROR(VLOOKUP(C3,Settings!$A$2:$F$5,2,FALSE)+(E3*D3+F3)*VLOOKUP(C3,Settings!$A$2:$F$5,3,FALSE)/100+(E3*D3+F3)*VLOOKUP(C3,Settings!$A$2:$F$5,4,FALSE)/100+VLOOKUP(C3,Settings!$A$2:$F$5,5,FALSE)+VLOOKUP(C3,Settings!$A$2:$F$5,6,FALSE),0)) | J3: =IF(B3="","",IF(ISNA(MATCH(B3,Inventory!$A$2:$A$201,0)),"Check product",E3*D3+F3-I3-G3-H3)) | K3: =IF(OR(B3="",NOT(ISNUMBER(J3)),E3*D3+F3=0),"",J3/(E3*D3+F3))
H4: =IFERROR(VLOOKUP(B4,Inventory!$A:$B,2,FALSE)*D4,0) | I4: =IF(C4="",0,IFERROR(VLOOKUP(C4,Settings!$A$2:$F$5,2,FALSE)+(E4*D4+F4)*VLOOKUP(C4,Settings!$A$2:$F$5,3,FALSE)/100+(E4*D4+F4)*VLOOKUP(C4,Settings!$A$2:$F$5,4,FALSE)/100+VLOOKUP(C4,Settings!$A$2:$F$5,5,FALSE)+VLOOKUP(C4,Settings!$A$2:$F$5,6,FALSE),0)) | J4: =IF(B4="","",IF(ISNA(MATCH(B4,Inventory!$A$2:$A$201,0)),"Check product",E4*D4+F4-I4-G4-H4)) | K4: =IF(OR(B4="",NOT(ISNUMBER(J4)),E4*D4+F4=0),"",J4/(E4*D4+F4))
H5: =IFERROR(VLOOKUP(B5,Inventory!$A:$B,2,FALSE)*D5,0) | I5: =IF(C5="",0,IFERROR(VLOOKUP(C5,Settings!$A$2:$F$5,2,FALSE)+(E5*D5+F5)*VLOOKUP(C5,Settings!$A$2:$F$5,3,FALSE)/100+(E5*D5+F5)*VLOOKUP(C5,Settings!$A$2:$F$5,4,FALSE)/100+VLOOKUP(C5,Settings!$A$2:$F$5,5,FALSE)+VLOOKUP(C5,Settings!$A$2:$F$5,6,FALSE),0)) | J5: =IF(B5="","",IF(ISNA(MATCH(B5,Inventory!$A$2:$A$201,0)),"Check product",E5*D5+F5-I5-G5-H5)) | K5: =IF(OR(B5="",NOT(ISNUMBER(J5)),E5*D5+F5=0),"",J5/(E5*D5+F5))
H6: =IFERROR(VLOOKUP(B6,Inventory!$A:$B,2,FALSE)*D6,0) | I6: =IF(C6="",0,IFERROR(VLOOKUP(C6,Settings!$A$2:$F$5,2,FALSE)+(E6*D6+F6)*VLOOKUP(C6,Settings!$A$2:$F$5,3,FALSE)/100+(E6*D6+F6)*VLOOKUP(C6,Settings!$A$2:$F$5,4,FALSE)/100+VLOOKUP(C6,Settings!$A$2:$F$5,5,FALSE)+VLOOKUP(C6,Settings!$A$2:$F$5,6,FALSE),0)) | J6: =IF(B6="","",IF(ISNA(MATCH(B6,Inventory!$A$2:$A$201,0)),"Check product",E6*D6+F6-I6-G6-H6)) | K6: =IF(OR(B6="",NOT(ISNUMBER(J6)),E6*D6+F6=0),"",J6/(E6*D6+F6))
H7: =IFERROR(VLOOKUP(B7,Inventory!$A:$B,2,FALSE)*D7,0) | I7: =IF(C7="",0,IFERROR(VLOOKUP(C7,Settings!$A$2:$F$5,2,FALSE)+(E7*D7+F7)*VLOOKUP(C7,Settings!$A$2:$F$5,3,FALSE)/100+(E7*D7+F7)*VLOOKUP(C7,Settings!$A$2:$F$5,4,FALSE)/100+VLOOKUP(C7,Settings!$A$2:$F$5,5,FALSE)+VLOOKUP(C7,Settings!$A$2:$F$5,6,FALSE),0)) | J7: =IF(B7="","",IF(ISNA(MATCH(B7,Inventory!$A$2:$A$201,0)),"Check product",E7*D7+F7-I7-G7-H7)) | K7: =IF(OR(B7="",NOT(ISNUMBER(J7)),E7*D7+F7=0),"",J7/(E7*D7+F7))
H8: =IFERROR(VLOOKUP(B8,Inventory!$A:$B,2,FALSE)*D8,0) | I8: =IF(C8="",0,IFERROR(VLOOKUP(C8,Settings!$A$2:$F$5,2,FALSE)+(E8*D8+F8)*VLOOKUP(C8,Settings!$A$2:$F$5,3,FALSE)/100+(E8*D8+F8)*VLOOKUP(C8,Settings!$A$2:$F$5,4,FALSE)/100+VLOOKUP(C8,Settings!$A$2:$F$5,5,FALSE)+VLOOKUP(C8,Settings!$A$2:$F$5,6,FALSE),0)) | J8: =IF(B8="","",IF(ISNA(MATCH(B8,Inventory!$A$2:$A$201,0)),"Check product",E8*D8+F8-I8-G8-H8)) | K8: =IF(OR(B8="",NOT(ISNUMBER(J8)),E8*D8+F8=0),"",J8/(E8*D8+F8))
H9: =IFERROR(VLOOKUP(B9,Inventory!$A:$B,2,FALSE)*D9,0) | I9: =IF(C9="",0,IFERROR(VLOOKUP(C9,Settings!$A$2:$F$5,2,FALSE)+(E9*D9+F9)*VLOOKUP(C9,Settings!$A$2:$F$5,3,FALSE)/100+(E9*D9+F9)*VLOOKUP(C9,Settings!$A$2:$F$5,4,FALSE)/100+VLOOKUP(C9,Settings!$A$2:$F$5,5,FALSE)+VLOOKUP(C9,Settings!$A$2:$F$5,6,FALSE),0)) | J9: =IF(B9="","",IF(ISNA(MATCH(B9,Inventory!$A$2:$A$201,0)),"Check product",E9*D9+F9-I9-G9-H9)) | K9: =IF(OR(B9="",NOT(ISNUMBER(J9)),E9*D9+F9=0),"",J9/(E9*D9+F9))
H10: =IFERROR(VLOOKUP(B10,Inventory!$A:$B,2,FALSE)*D10,0) | I10: =IF(C10="",0,IFERROR(VLOOKUP(C10,Settings!$A$2:$F$5,2,FALSE)+(E10*D10+F10)*VLOOKUP(C10,Settings!$A$2:$F$5,3,FALSE)/100+(E10*D10+F10)*VLOOKUP(C10,Settings!$A$2:$F$5,4,FALSE)/100+VLOOKUP(C10,Settings!$A$2:$F$5,5,FALSE)+VLOOKUP(C10,Settings!$A$2:$F$5,6,FALSE),0)) | J10: =IF(B10="","",IF(ISNA(MATCH(B10,Inventory!$A$2:$A$201,0)),"Check product",E10*D10+F10-I10-G10-H10)) | K10: =IF(OR(B10="",NOT(ISNUMBER(J10)),E10*D10+F10=0),"",J10/(E10*D10+F10))
H11: =IFERROR(VLOOKUP(B11,Inventory!$A:$B,2,FALSE)*D11,0) | I11: =IF(C11="",0,IFERROR(VLOOKUP(C11,Settings!$A$2:$F$5,2,FALSE)+(E11*D11+F11)*VLOOKUP(C11,Settings!$A$2:$F$5,3,FALSE)/100+(E11*D11+F11)*VLOOKUP(C11,Settings!$A$2:$F$5,4,FALSE)/100+VLOOKUP(C11,Settings!$A$2:$F$5,5,FALSE)+VLOOKUP(C11,Settings!$A$2:$F$5,6,FALSE),0)) | J11: =IF(B11="","",IF(ISNA(MATCH(B11,Inventory!$A$2:$A$201,0)),"Check product",E11*D11+F11-I11-G11-H11)) | K11: =IF(OR(B11="",NOT(ISNUMBER(J11)),E11*D11+F11=0),"",J11/(E11*D11+F11))
H12: =IFERROR(VLOOKUP(B12,Inventory!$A:$B,2,FALSE)*D12,0) | I12: =IF(C12="",0,IFERROR(VLOOKUP(C12,Settings!$A$2:$F$5,2,FALSE)+(E12*D12+F12)*VLOOKUP(C12,Settings!$A$2:$F$5,3,FALSE)/100+(E12*D12+F12)*VLOOKUP(C12,Settings!$A$2:$F$5,4,FALSE)/100+VLOOKUP(C12,Settings!$A$2:$F$5,5,FALSE)+VLOOKUP(C12,Settings!$A$2:$F$5,6,FALSE),0)) | J12: =IF(B12="","",IF(ISNA(MATCH(B12,Inventory!$A$2:$A$201,0)),"Check product",E12*D12+F12-I12-G12-H12)) | K12: =IF(OR(B12="",NOT(ISNUMBER(J12)),E12*D12+F12=0),"",J12/(E12*D12+F12))
H13: =IFERROR(VLOOKUP(B13,Inventory!$A:$B,2,FALSE)*D13,0) | I13: =IF(C13="",0,IFERROR(VLOOKUP(C13,Settings!$A$2:$F$5,2,FALSE)+(E13*D13+F13)*VLOOKUP(C13,Settings!$A$2:$F$5,3,FALSE)/100+(E13*D13+F13)*VLOOKUP(C13,Settings!$A$2:$F$5,4,FALSE)/100+VLOOKUP(C13,Settings!$A$2:$F$5,5,FALSE)+VLOOKUP(C13,Settings!$A$2:$F$5,6,FALSE),0)) | J13: =IF(B13="","",IF(ISNA(MATCH(B13,Inventory!$A$2:$A$201,0)),"Check product",E13*D13+F13-I13-G13-H13)) | K13: =IF(OR(B13="",NOT(ISNUMBER(J13)),E13*D13+F13=0),"",J13/(E13*D13+F13))
... H1001: =IFERROR(VLOOKUP(B1001,Inventory!$A:$B,2,FALSE)*D1001,0) | I1001: =IF(C1001="",0,IFERROR(VLOOKUP(C1001,Settings!$A$2:$F$5,2,FALSE)+(E1001*D1001+F1001)*VLOOKUP(C1001,Settings!$A$2:$F$5,3,FALSE)/100+(E1001*D1001+F1001)*VLOOKUP(C1001,Settings!$A$2:$F$5,4,FALSE)/100+VLOOKUP(C1001,Settings!$A$2:$F$5,5,FALSE)+VLOOKUP(C1001,Settings!$A$2:$F$5,6,FALSE),0)) | J1001: =IF(B1001="","",IF(ISNA(MATCH(B1001,Inventory!$A$2:$A$201,0)),"Check product",E1001*D1001+F1001-I1001-G1001-H1001)) | K1001: =IF(OR(B1001="",NOT(ISNUMBER(J1001)),E1001*D1001+F1001=0),"",J1001/(E1001*D1001+F1001))

Sheet Ad Spend
A1: Month (yyyy-mm) | B1: Marketplace | C1: Ad spend ($) | D1: Ad revenue ($) | E1: ROAS | F1: Verdict
E2: =IF(C2>0,D2/C2,"") | F2: =IF(E2="","",IF(E2>=3,"Scale",IF(E2>=1.5,"Watch","Losing money")))
E3: =IF(C3>0,D3/C3,"") | F3: =IF(E3="","",IF(E3>=3,"Scale",IF(E3>=1.5,"Watch","Losing money")))
E4: =IF(C4>0,D4/C4,"") | F4: =IF(E4="","",IF(E4>=3,"Scale",IF(E4>=1.5,"Watch","Losing money")))
E5: =IF(C5>0,D5/C5,"") | F5: =IF(E5="","",IF(E5>=3,"Scale",IF(E5>=1.5,"Watch","Losing money")))
E6: =IF(C6>0,D6/C6,"") | F6: =IF(E6="","",IF(E6>=3,"Scale",IF(E6>=1.5,"Watch","Losing money")))
E7: =IF(C7>0,D7/C7,"") | F7: =IF(E7="","",IF(E7>=3,"Scale",IF(E7>=1.5,"Watch","Losing money")))
E8: =IF(C8>0,D8/C8,"") | F8: =IF(E8="","",IF(E8>=3,"Scale",IF(E8>=1.5,"Watch","Losing money")))
E9: =IF(C9>0,D9/C9,"") | F9: =IF(E9="","",IF(E9>=3,"Scale",IF(E9>=1.5,"Watch","Losing money")))
E10: =IF(C10>0,D10/C10,"") | F10: =IF(E10="","",IF(E10>=3,"Scale",IF(E10>=1.5,"Watch","Losing money")))
E11: =IF(C11>0,D11/C11,"") | F11: =IF(E11="","",IF(E11>=3,"Scale",IF(E11>=1.5,"Watch","Losing money")))
E12: =IF(C12>0,D12/C12,"") | F12: =IF(E12="","",IF(E12>=3,"Scale",IF(E12>=1.5,"Watch","Losing money")))
E13: =IF(C13>0,D13/C13,"") | F13: =IF(E13="","",IF(E13>=3,"Scale",IF(E13>=1.5,"Watch","Losing money")))
... E61: =IF(C61>0,D61/C61,"") | F61: =IF(E61="","",IF(E61>=3,"Scale",IF(E61>=1.5,"Watch","Losing money")))
